ansys/api/cfx/VERSION
ansys/api/cfx/__init__.py
ansys/api/cfx/py.typed
ansys/api/cfx/v0/Connection.proto
ansys/api/cfx/v0/Connection_pb2.py
ansys/api/cfx/v0/Connection_pb2.pyi
ansys/api/cfx/v0/Connection_pb2_grpc.py
ansys/api/cfx/v0/Connection_pb2_grpc.pyi
ansys/api/cfx/v0/batch_ops.proto
ansys/api/cfx/v0/batch_ops_pb2.py
ansys/api/cfx/v0/batch_ops_pb2.pyi
ansys/api/cfx/v0/batch_ops_pb2_grpc.py
ansys/api/cfx/v0/batch_ops_pb2_grpc.pyi
ansys/api/cfx/v0/common.proto
ansys/api/cfx/v0/common_pb2.py
ansys/api/cfx/v0/common_pb2.pyi
ansys/api/cfx/v0/common_pb2_grpc.py
ansys/api/cfx/v0/common_pb2_grpc.pyi
ansys/api/cfx/v0/engine_eval.proto
ansys/api/cfx/v0/engine_eval_pb2.py
ansys/api/cfx/v0/engine_eval_pb2.pyi
ansys/api/cfx/v0/engine_eval_pb2_grpc.py
ansys/api/cfx/v0/engine_eval_pb2_grpc.pyi
ansys/api/cfx/v0/events.proto
ansys/api/cfx/v0/events_pb2.py
ansys/api/cfx/v0/events_pb2.pyi
ansys/api/cfx/v0/events_pb2_grpc.py
ansys/api/cfx/v0/events_pb2_grpc.pyi
ansys/api/cfx/v0/health.proto
ansys/api/cfx/v0/health_pb2.py
ansys/api/cfx/v0/health_pb2.pyi
ansys/api/cfx/v0/health_pb2_grpc.py
ansys/api/cfx/v0/health_pb2_grpc.pyi
ansys/api/cfx/v0/settings.proto
ansys/api/cfx/v0/settings_pb2.py
ansys/api/cfx/v0/settings_pb2.pyi
ansys/api/cfx/v0/settings_pb2_grpc.py
ansys/api/cfx/v0/settings_pb2_grpc.pyi
ansys_api_cfx-0.3.1.dist-info/licenses/AUTHORS
ansys_api_cfx-0.3.1.dist-info/licenses/LICENSE
ansys_api_cfx-0.3.1.dist-info/METADATA
ansys_api_cfx-0.3.1.dist-info/WHEEL
ansys_api_cfx-0.3.1.dist-info/entry_points.txt
ansys_api_cfx-0.3.1.dist-info/top_level.txt
ansys_api_cfx-0.3.1.dist-info/RECORD
