Metadata-Version: 2.4
Name: ansys-api-cfx
Version: 0.3.1
Summary: Autogenerated python gRPC interface package for ansys-api-cfx, built on 14:52:01 on 30 January 2026
Home-page: https://github.com/ansys-internal/ansys-api-cfx
Author: ANSYS, Inc.
Author-email: pyansys.core@ansys.com
Maintainer: ANSYS, Inc.
Maintainer-email: pyansys.core@ansys.com
License: MIT
Requires-Python: >=3.9,<4.0
License-File: LICENSE
License-File: AUTHORS
Requires-Dist: grpcio~=1.30
Requires-Dist: protobuf<5,>=3.19
Dynamic: author
Dynamic: author-email
Dynamic: description
Dynamic: description-content-type
Dynamic: home-page
Dynamic: license
Dynamic: license-file
Dynamic: maintainer
Dynamic: maintainer-email
Dynamic: requires-dist
Dynamic: requires-python
Dynamic: summary
